Workbook

Sheet Récap Site 2025
A1: MEAUX PN01 — CHARGES SITE 2025
A2: Site : MEAUX PN01 | Période : 01/01/2025 – 31/12/2025
A3: Fournisseur | B3: Date facture | C3: N° facture | D3: Description | E3: Montant HT (€) | F3: TVA (€) | G3: Montant TTC (€)
A4: ── CONTRAT MAINTENANCE ──
A5: Portails + Barrières automatiques
A6: DIRICKX | B6: 45658 | C6: 90694468 | D6: Site - Entretien portail 2025 | E6: 550.66 | F6: 110.13 | G6: 660.79
A7: Sous-total — Portails + Barrières automatiques | E7: =SUM(E6:E6) | F7: =SUM(F6:F6) | G7: =SUM(G6:G6)
A8: Vérifications règlementaires
A9: BUREAU VERITAS | B9: 46042 | C9: 26029889 | D9: Site - Rejet aqueux | E9: 835 | F9: 167 | G9: 1002
A10: BUREAU VERITAS | B10: 46042 | C10: 26029887 | D10: Site - Rejet atmosphériques | E10: 1800 | F10: 360 | G10: 2160
A11: BUREAU VERITAS | B11: 45945 | C11: 25616307 | D11: Site - Mesure bruits | E11: 1760 | F11: 352 | G11: 2112
A12: Sous-total — Vérifications règlementaires | E12: =SUM(E9:E11) | F12: =SUM(F9:F11) | G12: =SUM(G9:G11)
A13: ── CHARGES NON RECUPERABLES ──
A14: Frais Bancaires
A15: CIC | B15: 45667 | C15: Frais 01/25 | D15: Site - Commission du 10/01/25 | E15: 2.86 | G15: 2.86
A16: CIC | B16: 45726 | C16: Frais 03/25 | D16: Site - Commission du 10/03/25 | E16: 7.19 | G16: 7.19
A17: CIC | B17: 45789 | C17: Frais 05/25 | D17: Site - Commission du 12/05/25 | E17: 3.91 | G17: 3.91
A18: CIC | B18: 45818 | C18: Frais 06/25 | D18: Site - Commission du 10/06/25 | E18: 3.91 | G18: 3.91
A19: CIC | B19: 45880 | C19: Frais 08/25 | D19: Site - Commission du 11/08/25 | E19: 3.7 | G19: 3.7
A20: CIC | B20: 45940 | C20: Frais 10/25 | D20: Site - Commission du 10/10/25 | E20: 4.12 | G20: 4.12
A21: CIC | B21: 45971 | C21: Frais 11/25 | D21: Site - Commission du 10/11/25 | E21: 3.28 | G21: 3.28
A22: Sous-total — Frais Bancaires | E22: =SUM(E15:E21) | F22: =SUM(F15:F21) | G22: =SUM(G15:G21)
A24: TOTAL — CHARGES NON RÉCUPÉRABLES | E24: =E22
A26: TOTAL GÉNÉRAL — CHARGES RÉCUPÉRABLES | E26: =E7+E12

Sheet Récap MEAUX I 2025
A1: MEAUX PN01 — MEAUX I 2025
A2: Site : MEAUX PN01 | Période : 01/01/2025 – 31/12/2025
A3: Fournisseur | B3: Date facture | C3: N° facture | D3: Description | E3: Montant HT (€) | F3: TVA (€) | G3: Montant TTC (€)
A4: ── FLUIDES ──
A5: Electricité
A6: ENGIE | B6: 45860 | C6: 690000297954 | D6: Bât 1 - Electricité - Bornes recharge - 20/06 au 09/07/25 | E6: 377.68 | F6: 75.54 | G6: 453.22
A7: ENGIE | B7: 45883 | C7: 220008495571 | D7: Bât 1 - Electricité - Bornes recharge - 10/07 au 09/08/25 | E7: 301.17 | F7: 60.23 | G7: 361.4
A8: ENGIE | B8: 45905 | C8: 730000321384 | D8: Bât 1 - Electricité - Bornes recharge - 10/08 au 31/08/25 | E8: 354.34 | F8: 70.87 | G8: 425.21
A9: ENGIE | B9: 45975 | C9: 630000392015 | D9: Bât 1 - Electricité - Bornes recharge - 17/10 au 09/11/25 | E9: 351.37 | F9: 70.27 | G9: 421.64
A10: ENGIE | B10: 46003 | C10: 620001511822 | D10: Bât 1 - Electricité - Bornes recharge - 10/11 au 09/12/25 | E10: 290.14 | F10: 58.03 | G10: 348.17
A11: ENGIE | B11: 46107 | C11: 820001438853 | D11: Bât 1 - Electricité - Bornes recharge - 10/12 au 09/01/26 | E11: 299.81 | F11: 59.96 | G11: 359.77
A12: Sous-total — Electricité | E12: =SUM(E6:E11) | F12: =SUM(F6:F11) | G12: =SUM(G6:G11)
A13: ── CONTRAT MAINTENANCE ──
A14: Vérifications règlementaires
A15: BUREAU VERITAS | B15: 46071 | C15: 26099847 | D15: Bât 1 - Vérification efficacité energétique | E15: 700 | F15: 140 | G15: 840
A16: Sous-total — Vérifications règlementaires | E16: =SUM(E15:E15) | F16: =SUM(F15:F15) | G16: =SUM(G15:G15)
A17: ── TAXES ──
A18: Taxe Bureau & Stationnement
A19: TRESOR PUBLIC | B19: 45691 | C19: TB 25 BAT 1 | D19: Bât 1 - Taxe Bureaux | E19: 45514 | G19: 45514
A20: TRESOR PUBLIC | B20: 45691 | C20: TASS 25 BAT 1 | D20: Bât 1 - Taxe Annuelle de Stationnement | E20: 5909 | G20: 5909
A21: Sous-total — Taxe Bureau & Stationnement | E21: =SUM(E19:E20) | F21: =SUM(F19:F20) | G21: =SUM(G19:G20)
A22: ── CHARGES NON RECUPERABLES ──
A23: Entretien Courant
A24: BUREAU VERITAS | B24: 45709 | C24: 25002017 | D24: Bât 1 - Audit de fin de garantie décennale | E24: 5225 | F24: 1045 | G24: 6270
A25: BUREAU VERITAS | B25: 46014 | C25: 25800079 | D25: Bât 1 - DPE | E25: 1890 | F25: 378 | G25: 2268
A26: Sous-total — Entretien Courant | E26: =SUM(E24:E25) | F26: =SUM(F24:F25) | G26: =SUM(G24:G25)
A28: TOTAL — CHARGES NON RÉCUPÉRABLES | E28: =E26
A30: TOTAL GÉNÉRAL — CHARGES RÉCUPÉRABLES | E30: =E12+E16+E21

Sheet Récap MEAUX II 2025
A1: MEAUX PN01 — MEAUX II 2025
A2: Site : MEAUX PN01 | Période : 01/01/2025 – 31/12/2025
A3: Fournisseur | B3: Date facture | C3: N° facture | D3: Description | E3: Montant HT (€) | F3: TVA (€) | G3: Montant TTC (€)
A4: ── FLUIDES ──
A5: Eau
A6: SAUR | B6: 45875 | C6: 143251095968 | D6: Bât 2 - Eau - 1er Semestre 2025 | E6: 3893.61 | F6: 294.79 | G6: 4188.4
A7: SAUR | B7: 46021 | C7: 143251133813 | D7: Bât 2 - Eau - 2e Semestre 2025 | E7: 4197.62 | F7: 317.82 | G7: 4515.44
A8: Sous-total — Eau | E8: =SUM(E6:E7) | F8: =SUM(F6:F7) | G8: =SUM(G6:G7)
A9: Eau - Incendie
A10: SAUR | B10: 45861 | C10: 143251089373 | D10: Bât 2 - Eau incendie - 1er Semestre 2025 | E10: 1192.96 | F10: 90.32 | G10: 1283.28
A11: SAUR | B11: 46015 | C11: 143251127006 | D11: Bât 2 - Eau incendie - 2e Semestre 2025 | E11: 1279.1 | F11: 96.83 | G11: 1375.93
A12: Sous-total — Eau - Incendie | E12: =SUM(E10:E11) | F12: =SUM(F10:F11) | G12: =SUM(G10:G11)
A13: Electricité
A14: ENGIE | B14: 45716 | C14: 690000173551 | D14: Bât 2 - Electricité - Janvier 2025 | E14: 4929.91 | F14: 985.98 | G14: 5915.89
A15: ENGIE | B15: 45720 | C15: 760000203640 | D15: Bât 2 - Electricité - Février 2025 | E15: 4388.07 | F15: 877.61 | G15: 5265.68
A16: ENGIE | B16: 45750 | C16: 750000222782 | D16: Bât 2 - Electricité - Mars 2025 | E16: 4162.4 | F16: 832.48 | G16: 4994.88
A17: ENGIE | B17: 45780 | C17: 720001217478 | D17: Bât 2 - Electricité - Avril 2025 | E17: 3148.38 | F17: 629.68 | G17: 3778.06
A18: ENGIE | B18: 45813 | C18: 820006183065 | D18: Bât 2 - Electricité - Mai 2025 | E18: 3136.34 | F18: 627.27 | G18: 3763.61
A19: ENGIE | B19: 45843 | C19: 220008464987 | D19: Bât 2 - Electricité - Juin 2025 | E19: 3030.18 | F19: 606.04 | G19: 3636.22
A20: ENGIE | B20: 45874 | C20: 650000306105 | D20: Bât 2 - Electricité - Juillet 2025 | E20: 3106.96 | F20: 621.39 | G20: 3728.35
A21: ENGIE | B21: 45904 | C21: 650000320261 | D21: Bât 2 - Electricité - Août 2025 | E21: 3121.38 | F21: 624.28 | G21: 3745.66
A22: ENGIE | B22: 45934 | C22: 750000368041 | D22: Bât 2 - Electricité - Septembre 2025 | E22: 3050.16 | F22: 610.03 | G22: 3660.19
A23: ENGIE | B23: 45986 | C23: 820001348456 | D23: Bât 2 - Electricité - Octobre 2025 | E23: 3204.07 | F23: 640.81 | G23: 3844.88
A24: ENGIE | B24: 45995 | C24: 970006214475 | D24: Bât 2 - Electricité - Novembre 2025 | E24: 4629.57 | F24: 925.91 | G24: 5555.48
A25: ENGIE | B25: 46027 | C25: 760000419690 | D25: Bât 2 - Electricité - Décembre 2025 | E25: 6315.18 | F25: 1263.04 | G25: 7578.22
A26: Sous-total — Electricité | E26: =SUM(E14:E25) | F26: =SUM(F14:F25) | G26: =SUM(G14:G25)
A27: Gaz
A28: ENGIE | B28: 45694 | C28: 670000182108 | D28: Bât 2 - Gaz - Janvier 2025 | E28: 603.35 | F28: 50.67 | G28: 654.02
A29: ENGIE | B29: 45723 | C29: 740000258211 | D29: Bât 2 - Gaz - Février 2025 | E29: 555.4 | F29: 41.08 | G29: 596.48
A30: ENGIE | B30: 45751 | C30: 850005816723 | D30: Bât 2 - Gaz - Mars 2025 | E30: 554.4 | F30: 40.88 | G30: 595.28
A31: ENGIE | B31: 45783 | C31: 120009626935 | D31: Bât 2 - Gaz - Avril 2025 | E31: 554.4 | F31: 40.88 | G31: 595.28
A32: ENGIE | B32: 45812 | C32: 320007759177 | D32: Bât 2 - Gaz - Mai 2025 | E32: 563.64 | F32: 42.73 | G32: 606.37
A33: ENGIE | B33: 45842 | C33: 850005885257 | D33: Bât 2 - Gaz - Juin 2025 | E33: 554.4 | F33: 40.88 | G33: 595.28
A34: ENGIE | B34: 45873 | C34: 420006864904 | D34: Bât 2 - Gaz - Juillet 2025 | E34: 557.12 | F34: 41.22 | G34: 598.34
A35: ENGIE | B35: 45904 | C35: 850005934224 | D35: Bât 2 - Gaz - Août 2025 | E35: 557.12 | F35: 111.42 | G35: 668.54
A36: ENGIE | B36: 45933 | C36: 690000351291 | D36: Bât 2 - Gaz - Septembre 2025 | E36: 224.8 | F36: 44.96 | G36: 269.76
A37: ENGIE | B37: 45965 | C37: 320007853625 | D37: Bât 2 - Gaz - Octobre 2025 | E37: 224.8 | F37: 44.96 | G37: 269.76
A38: ENGIE | B38: 45993 | C38: 40017179466 | D38: Bât 2 - Gaz - Novembre 2025 | E38: 303.68 | F38: 60.74 | G38: 364.42
A39: ENGIE | B39: 46028 | C39: 640000378012 | D39: Bât 2 - Gaz - Décembre 2025 | E39: 224.8 | F39: 44.96 | G39: 269.76
A40: Sous-total — Gaz | E40: =SUM(E28:E39) | F40: =SUM(F28:F39) | G40: =SUM(G28:G39)
A41: ── HONORAIRES ──
A42: Honoraires Divers
A43: C-JUSTICE | B43: 45980 | C43: 25.11.5229 | D43: Bât 2 - PV Constat - 50% EDLE du 07/11 Delisle | E43: 300 | F43: 60 | G43: 360
A44: CJCE | B44: 45997 | C44: 25-15258 | D44: Bât 2 - PV Constat - 50% EDLE du 25/11 SHAOKE | E44: 400 | F44: 80 | G44: 480
A45: Sous-total — Honoraires Divers | E45: =SUM(E43:E44) | F45: =SUM(F43:F44) | G45: =SUM(G43:G44)
A46: ── TRAVAUX ──
A47: Entretien Courant
A48: AAI | B48: 45793 | C48: 90117651 | D48: Bât 2 - Remplac. Tresses pompes | E48: 1535 | F48: 307 | G48: 1842
A49: AAI | B49: 45777 | C49: 90117212 | D49: Bât 2 - Remplacement du thermoplongeur et joints klyngérites | E49: 2389 | F49: 477.8 | G49: 2866.8
A50: SOPREMA | B50: 45818 | C50: 25.15.2.6261 | D50: Bât 2 - Débouchage EEP siphoides obstruées suite maintenace | E50: 2220 | F50: 444 | G50: 2664
A51: MADIS | B51: 45849 | C51: FA2507-0599 | D51: Bät 2 - Contrôle de poteau incendie en simultané | E51: 1340 | F51: 268 | G51: 1608
A52: AAI | B52: 46044 | C52: 90130177 | D52: Bât 2 - Remplacement arbre moteur | E52: 6442 | F52: 1288.4 | G52: 7730.4
A53: DIRICKX | B53: 45866 | C53: 90753857 | D53: Bât 2 - Remplac. détecteur boucle portail | E53: 155.13 | F53: 31.03 | G53: 186.16
A54: SMGE | B54: 45940 | C54: F251019 | D54: Bât 2 - Dépannage SSI du 09/25 | E54: 300 | F54: 60 | G54: 360
A55: CVC | B55: 45954 | C55: 25.10.8554 | D55: Bât 2 - Dépannage défaut chaufferie | E55: 250 | F55: 50 | G55: 300
A56: FIVO | B56: 45930 | C56: FACT04924 | D56: Bât 2 - Dépannage PCF du 29/09/25 | E56: 850 | F56: 170 | G56: 1020
A57: CVC | B57: 45988 | C57: 25.11.8609 | D57: Bât 2 - Entretien de la climatisation et CTA | E57: 3940 | F57: 788 | G57: 4728
A58: CVC | B58: 45987 | C58: 25.11.8607 | D58: Bât 2 - Régul. dépannage fuite quai 19 | E58: 1114.63 | F58: 222.93 | G58: 1337.56
A59: CVC | B59: 46002 | C59: 25.12.8631 | D59: Bât 2 - Accompagnement Bureau Veritas vérif. énergétique | E59: 165 | F59: 33 | G59: 198
... A62: SMGE | B62: 46083 | C62: F251212 | D62: Bât 2 - Interv panne SSI du 22/12/25 | E62: 1950 | F62: 390 | G62: 2340
A63: Sous-total — Entretien Courant | E63: =SUM(E48:E62) | F63: =SUM(F48:F62) | G63: =SUM(G48:G62)
A64: ── CONTRAT MAINTENANCE ──
A65: Ascenseur
A66: OTIS | B66: 46024 | C66: 8544830 | D66: Bât 2 - Entretien Ascenseur - Décembre 2025 | E66: 131.67 | F66: 26.33 | G66: 158
A67: Sous-total — Ascenseur | E67: =SUM(E66:E66) | F67: =SUM(F66:F66) | G67: =SUM(G66:G66)
A68: Chaufferie
A69: CVC MAINTENANCE | B69: 45677 | C69: FAC25-01-8248 | D69: Bât 2 - Entretien chauffage - 1er Semestre 2025 | E69: 2488.8 | F69: 497.76 | G69: 2986.56
A70: CVC MAINTENANCE | B70: 45840 | C70: FAC25-07-8473 | D70: Bât 2 - Entretien chauffage - 2e Semestre 2025 | E70: 2488.8 | F70: 497.76 | G70: 2986.56
A71: Sous-total — Chaufferie | E71: =SUM(E69:E70) | F71: =SUM(F69:F70) | G71: =SUM(G69:G70)
A72: Désenfumage
A73: IDEA | B73: 45713 | C73: 25020037 | D73: Bât 2 - Entretien désenfumage 2025 | E73: 3978 | F73: 795.6 | G73: 4773.6
A74: Sous-total — Désenfumage | E74: =SUM(E73:E73) | F74: =SUM(F73:F73) | G74: =SUM(G73:G73)
A75: Espaces verts
A76: MUGO | B76: 45688 | C76: MP25010165 | D76: Bât 2 - Entretien espaces verts - 1er Trimestre | E76: 2920.32 | F76: 584.06 | G76: 3504.38
A77: MUGO | B77: 45775 | C77: MP25041932 | D77: Bât 2 - Entretien espaces verts - Avril | E77: 973.44 | F77: 194.69 | G77: 1168.13
A78: MUGO | B78: 45805 | C78: MP25052467 | D78: Bât 2 - Entretien espaces verts - Mai & Juin | E78: 1946.88 | F78: 389.38 | G78: 2336.26
A79: MUGO | B79: 45869 | C79: MP25073698 | D79: Bât 2 - Entretien espaces verts - 3e Trimestre | E79: 2920.32 | F79: 584.06 | G79: 3504.38
A80: MUGO | B80: 45959 | C80: MP25105254 | D80: Bât 2 - Entretien espaces verts - 4e Trimestre | E80: 2920.32 | F80: 584.06 | G80: 3504.38
A81: Sous-total — Espaces verts | E81: =SUM(E76:E80) | F81: =SUM(F76:F80) | G81: =SUM(G76:G80)
A82: Portails + Barrières automatiques
A83: DIRICKX | B83: 45658 | C83: 90694469 | D83: Bât 2 - Entretien portail et barrières 2025 | E83: 1993.75 | F83: 398.75 | G83: 2392.5
A84: Sous-total — Portails + Barrières automatiques | E84: =SUM(E83:E83) | F84: =SUM(F83:F83) | G84: =SUM(G83:G83)
A85: Portes Coupe-Feu
A86: FIVO | B86: 45733 | C86: FACT04112 | D86: Bât 2 - Entretien PCF 2025 | E86: 2068.74 | F86: 413.75 | G86: 2482.49
A87: Sous-total — Portes Coupe-Feu | E87: =SUM(E86:E86) | F87: =SUM(F86:F86) | G87: =SUM(G86:G86)
A88: Protection foudre
A89: 1G FOUDRE | B89: 45688 | C89: F2501-0031 | D89: Bât 2 - Entretien protection foudre complète 2025 | E89: 1150 | F89: 230 | G89: 1380
A90: Sous-total — Protection foudre | E90: =SUM(E89:E89) | F90: =SUM(F89:F89) | G90: =SUM(G89:G89)
A91: Quais & Portes sectionnelles
A92: PROQUAI | B92: 45828 | C92: PAFC004643 | D92: Bât 2 - Entretien quais niveleurs & portes sectionnelles 2025 | E92: 5397 | F92: 1079.4 | G92: 6476.4
A93: Sous-total — Quais & Portes sectionnelles | E93: =SUM(E92:E92) | F93: =SUM(F92:F92) | G93: =SUM(G92:G92)
A94: Séparateur hydro.
A95: A3 SERVICES | B95: 45979 | C95: F0005252 | D95: Bât 2 - Entretien séparateur hydro. station relevage et disconnecteur | E95: 3536.4 | F95: 707.28 | G95: 4243.68
A96: Sous-total — Séparateur hydro. | E96: =SUM(E95:E95) | F96: =SUM(F95:F95) | G96: =SUM(G95:G95)
A97: Sprinklers - RIA - PI - Fioul
A98: AAI | B98: 45709 | C98: 90113537 | D98: Bât 2 - Entretien SPK - RIA - PI + Fioul - 1 Trim 2025 | E98: 7428.14 | F98: 1485.63 | G98: 8913.77
A99: AAI | B99: 45790 | C99: 90117464 | D99: Bât 2 - Entretien SPK - RIA - PI + Fioul - 2 Trim 2025 | E99: 7428.14 | F99: 1485.63 | G99: 8913.77
A100: AAI | B100: 45870 | C100: 90121899 | D100: Bât 2 - Entretien SPK - RIA - PI + Fioul - 3 Trim 2025 | E100: 7428.14 | F100: 1485.63 | G100: 8913.77
A101: AAI | B101: 45938 | C101: 90124955 | D101: Bât 2 - Entretien SPK - RIA - PI + Fioul - 4 Trim 2025 | E101: 7428.14 | F101: 1485.63 | G101: 8913.77
A102: Sous-total — Sprinklers - RIA - PI - Fioul | E102: =SUM(E98:E101) | F102: =SUM(F98:F101) | G102: =SUM(G98:G101)
...

Sheet Paramètres
A1: MEAUX PN01 — PARAMÈTRES SITE 2025
A2: Site | C2: MEAUX PN01
A3: Surface totale site (m²) | C3: 71243.4
A4: Année | C4: 2025
A6: Lot | B6: Statut | C6: Surface (m²) | D6: Bâtiment | E6: Locataire | F6: Début de bail / MAD | G6: Fin de bail | H6: Jours Fluides 2025 | I6: Prorata Fluides | J6: Jours Autres 2025 | K6: Prorata Autres
A7: BAT 1 - MEAUX I | B7: Occupé | C7: 32653.4 | D7: MEAUX I | E7: C&A | F7: 42111 | G7: 46493 | H7: =MAX(0,MIN(DATE(2025,12,31),IF(G7="",DATE(2025,12,31),G7))-MAX(DATE(2025,1,1),IF(F7="",DATE(2025,1,1),F7))+1) | I7: =H7/365 | J7: =H7 | K7: =J7/365
A8: C1 | B8: Occupé | C8: 9553 | D8: MEAUX II | E8: DELISLE Logistique | F8: 45968 | G8: 50344 | H8: 55 | I8: =H8/365 | J8: 31 | K8: =J8/365
A9: C2 | B9: Vacant | C9: 9717.5 | D9: MEAUX II | H9: =MAX(0,MIN(DATE(2025,12,31),IF(G9="",DATE(2025,12,31),G9))-MAX(DATE(2025,1,1),IF(F9="",DATE(2025,1,1),F9))+1) | I9: =H9/365 | J9: =H9 | K9: =J9/365
A10: C3 | B10: Occupé | C10: 9525 | D10: MEAUX II | E10: SHAOKE Express | F10: 45986 | G10: 50419 | H10: 37 | I10: =H10/365 | J10: 0 | K10: =J10/365
A11: C4 | B11: Vacant | C11: 9794.5 | D11: MEAUX II | H11: =MAX(0,MIN(DATE(2025,12,31),IF(G11="",DATE(2025,12,31),G11))-MAX(DATE(2025,1,1),IF(F11="",DATE(2025,1,1),F11))+1) | I11: =H11/365 | J11: =H11 | K11: =J11/365
A13: Poste (lié aux Récapitulatifs) | C13: Montant HT (€)
A14: =IFERROR(MID('Récap MEAUX II 2025'!A84,FIND(" — ",'Récap MEAUX II 2025'!A84)+4,100),"") | C14: ='Récap MEAUX II 2025'!E84
A15: =IFERROR(MID('Récap MEAUX II 2025'!A127,FIND(" — ",'Récap MEAUX II 2025'!A127)+4,100),"") | C15: ='Récap MEAUX II 2025'!E127
A16: =IFERROR(MID('Récap Site 2025'!A22,FIND(" — ",'Récap Site 2025'!A22)+4,100),"") | C16: ='Récap Site 2025'!E22
A17: =IFERROR(MID('Récap MEAUX II 2025'!A26,FIND(" — ",'Récap MEAUX II 2025'!A26)+4,100),"") | C17: ='Récap MEAUX II 2025'!E26
A18: =IFERROR(MID('Récap MEAUX II 2025'!A132,FIND(" — ",'Récap MEAUX II 2025'!A132)+4,100),"") | C18: ='Récap MEAUX II 2025'!E132
A19: =IFERROR(MID('Récap MEAUX II 2025'!A148,FIND(" — ",'Récap MEAUX II 2025'!A148)+4,100),"") | C19: ='Récap MEAUX II 2025'!E148
A20: =IFERROR(MID('Récap MEAUX II 2025'!A8,FIND(" — ",'Récap MEAUX II 2025'!A8)+4,100),"") | C20: ='Récap MEAUX II 2025'!E8
A21: =IFERROR(MID('Récap MEAUX II 2025'!A12,FIND(" — ",'Récap MEAUX II 2025'!A12)+4,100),"") | C21: ='Récap MEAUX II 2025'!E12
A22: =IFERROR(MID('Récap MEAUX II 2025'!A40,FIND(" — ",'Récap MEAUX II 2025'!A40)+4,100),"") | C22: ='Récap MEAUX II 2025'!E40
A23: =IFERROR(MID('Récap MEAUX II 2025'!A45,FIND(" — ",'Récap MEAUX II 2025'!A45)+4,100),"") | C23: ='Récap MEAUX II 2025'!E45
A24: =IFERROR(MID('Récap MEAUX II 2025'!A63,FIND(" — ",'Récap MEAUX II 2025'!A63)+4,100),"") | C24: ='Récap MEAUX II 2025'!E63
A25: =IFERROR(MID('Récap MEAUX II 2025'!A67,FIND(" — ",'Récap MEAUX II 2025'!A67)+4,100),"") | C25: ='Récap MEAUX II 2025'!E67
A26: =IFERROR(MID('Récap MEAUX II 2025'!A71,FIND(" — ",'Récap MEAUX II 2025'!A71)+4,100),"") | C26: ='Récap MEAUX II 2025'!E71
A27: =IFERROR(MID('Récap MEAUX II 2025'!A74,FIND(" — ",'Récap MEAUX II 2025'!A74)+4,100),"") | C27: ='Récap MEAUX II 2025'!E74
A28: =IFERROR(MID('Récap MEAUX II 2025'!A81,FIND(" — ",'Récap MEAUX II 2025'!A81)+4,100),"") | C28: ='Récap MEAUX II 2025'!E81
A29: =IFERROR(MID('Récap MEAUX II 2025'!A87,FIND(" — ",'Récap MEAUX II 2025'!A87)+4,100),"") | C29: ='Récap MEAUX II 2025'!E87
A30: =IFERROR(MID('Récap MEAUX II 2025'!A90,FIND(" — ",'Récap MEAUX II 2025'!A90)+4,100),"") | C30: ='Récap MEAUX II 2025'!E90
A31: =IFERROR(MID('Récap MEAUX II 2025'!A93,FIND(" — ",'Récap MEAUX II 2025'!A93)+4,100),"") | C31: ='Récap MEAUX II 2025'!E93
A32: =IFERROR(MID('Récap MEAUX II 2025'!A96,FIND(" — ",'Récap MEAUX II 2025'!A96)+4,100),"") | C32: ='Récap MEAUX II 2025'!E96
A33: =IFERROR(MID('Récap MEAUX II 2025'!A102,FIND(" — ",'Récap MEAUX II 2025'!A102)+4,100),"") | C33: ='Récap MEAUX II 2025'!E102
A34: =IFERROR(MID('Récap MEAUX II 2025'!A105,FIND(" — ",'Récap MEAUX II 2025'!A105)+4,100),"") | C34: ='Récap MEAUX II 2025'!E105
A35: =IFERROR(MID('Récap MEAUX II 2025'!A119,FIND(" — ",'Récap MEAUX II 2025'!A119)+4,100),"") | C35: ='Récap MEAUX II 2025'!E119
A36: =IFERROR(MID('Récap MEAUX II 2025'!A123,FIND(" — ",'Récap MEAUX II 2025'!A123)+4,100),"") | C36: ='Récap MEAUX II 2025'!E123
A37: =IFERROR(MID('Récap MEAUX II 2025'!A154,FIND(" — ",'Récap MEAUX II 2025'!A154)+4,100),"") | C37: ='Récap MEAUX II 2025'!E154

Sheet BAT 1 - MEAUX I
A1: RÉGULARISATION DE CHARGES — BAT 1 - MEAUX I
A2: Site : MEAUX PN01 | Année 2025
A3: =Paramètres!$B$7&IF(Paramètres!$E$7<>""," — "&Paramètres!$E$7,"")
A4: Poste | B4: Clé répartition | C4: Total HT | D4: QP annuelle | E4: Période | F4: QP locataire
A5: CHARGES SITE — MEAUX PN01
A6: CONTRAT MAINTENANCE
A7: Portails + Barrières automatiques | B7: =Paramètres!$C$7/Paramètres!$C$3 | C7: ='Récap MEAUX II 2025'!E84 | D7: =B7*C7 | E7: =Paramètres!$J$7/365 | F7: =D7*E7
A8: Vérifications règlementaires | B8: =Paramètres!$C$7/Paramètres!$C$3 | C8: ='Récap MEAUX II 2025'!E127 | D8: =B8*C8 | E8: =Paramètres!$J$7/365 | F8: =D8*E8
A9: Sous-total — CONTRAT MAINTENANCE | C9: =SUM(C7:C8) | D9: =SUM(D7:D8) | F9: =SUM(F7:F8)
A11: CHARGES BÂTIMENT — MEAUX I
A12: FLUIDES
A13: Electricité | B13: =Paramètres!$C$7/32653.4 | C13: ='Récap MEAUX II 2025'!E26 | D13: =B13*C13 | E13: =Paramètres!$H$7/365 | F13: =D13*E13
A14: Sous-total — FLUIDES | C14: =SUM(C13:C13) | D14: =SUM(D13:D13) | F14: =SUM(F13:F13)
A15: CONTRAT MAINTENANCE
A16: Vérifications règlementaires | B16: =Paramètres!$C$7/32653.4 | C16: ='Récap MEAUX II 2025'!E127 | D16: =B16*C16 | E16: =Paramètres!$J$7/365 | F16: =D16*E16
A17: Sous-total — CONTRAT MAINTENANCE | C17: =SUM(C16:C16) | D17: =SUM(D16:D16) | F17: =SUM(F16:F16)
A18: TAXES
A19: Taxe Bureau & Stationnement | B19: =Paramètres!$C$7/32653.4 | C19: ='Récap MEAUX II 2025'!E132 | D19: =B19*C19 | E19: =Paramètres!$J$7/365 | F19: =D19*E19
A20: Sous-total — TAXES | C20: =SUM(C19:C19) | D20: =SUM(D19:D19) | F20: =SUM(F19:F19)
A23: HONORAIRES
A24: Honoraires Gestion Technique | E24: 1 | F24: =IF(D24="","",D24*E24)
A25: Sous-total — HONORAIRES | C25: =SUM(C24:C24) | D25: =SUM(D24:D24) | F25: =SUM(F24:F24)
A27: TOTAL CHARGES RÉCUPÉRABLES RÉELLES (€ HT) | C27: =C9+C14+C17+C20+C25 | D27: =D9+D14+D17+D20+D25 | F27: =F9+F14+F17+F20+F25
A29: Provisions pour charges versées | D29: Montant annuel (€) | F29: Montant locataire (€)
A30: 1er trimestre (T1)
A31: 2e trimestre (T2)
A32: 3e trimestre (T3)
A33: 4e trimestre (T4)
A34: Total provisions pour charges versées → | D34: =SUM(D30:D33) | F34: =SUM(F30:F33)
A36: =IF(F27-F34>0,"SOLDE DÉBITEUR","SOLDE CRÉDITEUR") | D36: =D27-D34 | F36: =F27-F34
A38: ℹ Clé répartition = surface lot ÷ surface totale site. Période = nombre de jours d'occupation ÷ 365.

Sheet C1
A1: RÉGULARISATION DE CHARGES — C1
A2: Site : MEAUX PN01 | Année 2025
A3: =Paramètres!$B$8&IF(Paramètres!$E$8<>""," — "&Paramètres!$E$8,"")
A4: Poste | B4: Clé répartition | C4: Total HT | D4: QP annuelle | E4: Période | F4: QP locataire
A5: CHARGES SITE — MEAUX PN01
A6: CONTRAT MAINTENANCE
A7: Portails + Barrières automatiques | B7: =Paramètres!$C$8/Paramètres!$C$3 | C7: ='Récap MEAUX II 2025'!E84 | D7: =B7*C7 | E7: =Paramètres!$J$8/365 | F7: =D7*E7
A8: Vérifications règlementaires | B8: =Paramètres!$C$8/Paramètres!$C$3 | C8: ='Récap MEAUX II 2025'!E127 | D8: =B8*C8 | E8: =Paramètres!$J$8/365 | F8: =D8*E8
A9: Sous-total — CONTRAT MAINTENANCE | C9: =SUM(C7:C8) | D9: =SUM(D7:D8) | F9: =SUM(F7:F8)
A11: CHARGES BÂTIMENT — MEAUX II
A12: FLUIDES
A13: Eau | B13: =Paramètres!$C$8/38590.0 | C13: ='Récap MEAUX II 2025'!E8 | D13: =B13*C13 | E13: =Paramètres!$H$8/365 | F13: =D13*E13
A14: Eau - Incendie | B14: =Paramètres!$C$8/38590.0 | C14: ='Récap MEAUX II 2025'!E12 | D14: =B14*C14 | E14: =Paramètres!$H$8/365 | F14: =D14*E14
A15: Electricité | B15: =Paramètres!$C$8/38590.0 | C15: ='Récap MEAUX II 2025'!E26 | D15: =B15*C15 | E15: =Paramètres!$H$8/365 | F15: =D15*E15
A16: Gaz | B16: =Paramètres!$C$8/38590.0 | C16: ='Récap MEAUX II 2025'!E40 | D16: =B16*C16 | E16: =Paramètres!$H$8/365 | F16: =D16*E16
A17: Sous-total — FLUIDES | C17: =SUM(C13:C16) | D17: =SUM(D13:D16) | F17: =SUM(F13:F16)
A18: HONORAIRES
A19: Honoraires Divers | B19: =Paramètres!$C$8/38590.0 | C19: ='Récap MEAUX II 2025'!E45 | D19: =B19*C19 | E19: =Paramètres!$J$8/365 | F19: =D19*E19
A20: Sous-total — HONORAIRES | C20: =SUM(C19:C19) | D20: =SUM(D19:D19) | F20: =SUM(F19:F19)
A21: TRAVAUX
A22: Entretien Courant | B22: =Paramètres!$C$8/38590.0 | C22: ='Récap MEAUX II 2025'!E63 | D22: =B22*C22 | E22: =Paramètres!$J$8/365 | F22: =D22*E22
A23: Sous-total — TRAVAUX | C23: =SUM(C22:C22) | D23: =SUM(D22:D22) | F23: =SUM(F22:F22)
A24: CONTRAT MAINTENANCE
A25: Ascenseur | B25: =Paramètres!$C$8/38590.0 | C25: ='Récap MEAUX II 2025'!E67 | D25: =B25*C25 | E25: =Paramètres!$J$8/365 | F25: =D25*E25
A26: Chaufferie | B26: =Paramètres!$C$8/38590.0 | C26: ='Récap MEAUX II 2025'!E71 | D26: =B26*C26 | E26: =Paramètres!$J$8/365 | F26: =D26*E26
A27: Désenfumage | B27: =Paramètres!$C$8/38590.0 | C27: ='Récap MEAUX II 2025'!E74 | D27: =B27*C27 | E27: =Paramètres!$J$8/365 | F27: =D27*E27
A28: Espaces verts | B28: =Paramètres!$C$8/38590.0 | C28: ='Récap MEAUX II 2025'!E81 | D28: =B28*C28 | E28: =Paramètres!$J$8/365 | F28: =D28*E28
A29: Portails + Barrières automatiques | B29: =Paramètres!$C$8/38590.0 | C29: ='Récap MEAUX II 2025'!E84 | D29: =B29*C29 | E29: =Paramètres!$J$8/365 | F29: =D29*E29
A30: Portes Coupe-Feu | B30: =Paramètres!$C$8/38590.0 | C30: ='Récap MEAUX II 2025'!E87 | D30: =B30*C30 | E30: =Paramètres!$J$8/365 | F30: =D30*E30
A31: Protection foudre | B31: =Paramètres!$C$8/38590.0 | C31: ='Récap MEAUX II 2025'!E90 | D31: =B31*C31 | E31: =Paramètres!$J$8/365 | F31: =D31*E31
A32: Quais & Portes sectionnelles | B32: =Paramètres!$C$8/38590.0 | C32: ='Récap MEAUX II 2025'!E93 | D32: =B32*C32 | E32: =Paramètres!$J$8/365 | F32: =D32*E32
A33: Séparateur hydro. | B33: =Paramètres!$C$8/38590.0 | C33: ='Récap MEAUX II 2025'!E96 | D33: =B33*C33 | E33: =Paramètres!$J$8/365 | F33: =D33*E33
A34: Sprinklers - RIA - PI - Fioul | B34: =Paramètres!$C$8/38590.0 | C34: ='Récap MEAUX II 2025'!E102 | D34: =B34*C34 | E34: =Paramètres!$J$8/365 | F34: =D34*E34
A35: SSI | B35: =Paramètres!$C$8/38590.0 | C35: ='Récap MEAUX II 2025'!E105 | D35: =B35*C35 | E35: =Paramètres!$J$8/365 | F35: =D35*E35
A36: Télésurveillance | B36: =Paramètres!$C$8/38590.0 | C36: ='Récap MEAUX II 2025'!E119 | D36: =B36*C36 | E36: =Paramètres!$J$8/365 | F36: =D36*E36
A37: Toiture | B37: =Paramètres!$C$8/38590.0 | C37: ='Récap MEAUX II 2025'!E123 | D37: =B37*C37 | E37: =Paramètres!$J$8/365 | F37: =D37*E37
A38: Vérifications règlementaires | B38: =Paramètres!$C$8/38590.0 | C38: ='Récap MEAUX II 2025'!E127 | D38: =B38*C38 | E38: =Paramètres!$J$8/365 | F38: =D38*E38
A39: Sous-total — CONTRAT MAINTENANCE | C39: =SUM(C25:C38) | D39: =SUM(D25:D38) | F39: =SUM(F25:F38)
A40: TAXES
A41: Taxe Bureau & Stationnement | B41: =Paramètres!$C$8/38590.0 | C41: ='Récap MEAUX II 2025'!E132 | D41: =B41*C41 | E41: =Paramètres!$J$8/365 | F41: =D41*E41
A42: Sous-total — TAXES | C42: =SUM(C41:C41) | D42: =SUM(D41:D41) | F42: =SUM(F41:F41)
A45: TOTAL CHARGES RÉCUPÉRABLES RÉELLES (€ HT) | C45: =C9+C17+C20+C23+C39+C42 | D45: =D9+D17+D20+D23+D39+D42 | F45: =F9+F17+F20+F23+F39+F42
A47: Provisions pour charges versées | D47: Montant annuel (€) | F47: Montant locataire (€)
A48: 1er trimestre (T1)
A49: 2e trimestre (T2)
A50: 3e trimestre (T3)
A51: 4e trimestre (T4)
A52: Total provisions pour charges versées → | D52: =SUM(D48:D51) | F52: =SUM(F48:F51)
A54: =IF(F45-F52>0,"SOLDE DÉBITEUR","SOLDE CRÉDITEUR") | D54: =D45-D52 | F54: =F45-F52
A56: ℹ Clé répartition = surface lot ÷ surface totale site. Période = nombre de jours d'occupation ÷ 365.

Sheet C2
A1: RÉGULARISATION DE CHARGES — C2
A2: Site : MEAUX PN01 | Année 2025
A3: =Paramètres!$B$9&IF(Paramètres!$E$9<>""," — "&Paramètres!$E$9,"")
A4: Poste | B4: Clé répartition | C4: Total HT | D4: QP annuelle | E4: Période | F4: QP locataire
A5: CHARGES SITE — MEAUX PN01
A6: CONTRAT MAINTENANCE
A7: Portails + Barrières automatiques | B7: =Paramètres!$C$9/Paramètres!$C$3 | C7: ='Récap MEAUX II 2025'!E84 | D7: =B7*C7 | E7: =Paramètres!$J$9/365 | F7: =D7*E7
A8: Vérifications règlementaires | B8: =Paramètres!$C$9/Paramètres!$C$3 | C8: ='Récap MEAUX II 2025'!E127 | D8: =B8*C8 | E8: =Paramètres!$J$9/365 | F8: =D8*E8
A9: Sous-total — CONTRAT MAINTENANCE | C9: =SUM(C7:C8) | D9: =SUM(D7:D8) | F9: =SUM(F7:F8)
A11: CHARGES BÂTIMENT — MEAUX II
A12: FLUIDES
A13: Eau | B13: =Paramètres!$C$9/38590.0 | C13: ='Récap MEAUX II 2025'!E8 | D13: =B13*C13 | E13: =Paramètres!$H$9/365 | F13: =D13*E13
A14: Eau - Incendie | B14: =Paramètres!$C$9/38590.0 | C14: ='Récap MEAUX II 2025'!E12 | D14: =B14*C14 | E14: =Paramètres!$H$9/365 | F14: =D14*E14
A15: Electricité | B15: =Paramètres!$C$9/38590.0 | C15: ='Récap MEAUX II 2025'!E26 | D15: =B15*C15 | E15: =Paramètres!$H$9/365 | F15: =D15*E15
A16: Gaz | B16: =Paramètres!$C$9/38590.0 | C16: ='Récap MEAUX II 2025'!E40 | D16: =B16*C16 | E16: =Paramètres!$H$9/365 | F16: =D16*E16
A17: Sous-total — FLUIDES | C17: =SUM(C13:C16) | D17: =SUM(D13:D16) | F17: =SUM(F13:F16)
A18: HONORAIRES
A19: Honoraires Divers | B19: =Paramètres!$C$9/38590.0 | C19: ='Récap MEAUX II 2025'!E45 | D19: =B19*C19 | E19: =Paramètres!$J$9/365 | F19: =D19*E19
A20: Sous-total — HONORAIRES | C20: =SUM(C19:C19) | D20: =SUM(D19:D19) | F20: =SUM(F19:F19)
A21: TRAVAUX
A22: Entretien Courant | B22: =Paramètres!$C$9/38590.0 | C22: ='Récap MEAUX II 2025'!E63 | D22: =B22*C22 | E22: =Paramètres!$J$9/365 | F22: =D22*E22
A23: Sous-total — TRAVAUX | C23: =SUM(C22:C22) | D23: =SUM(D22:D22) | F23: =SUM(F22:F22)
A24: CONTRAT MAINTENANCE
A25: Ascenseur | B25: =Paramètres!$C$9/38590.0 | C25: ='Récap MEAUX II 2025'!E67 | D25: =B25*C25 | E25: =Paramètres!$J$9/365 | F25: =D25*E25
A26: Chaufferie | B26: =Paramètres!$C$9/38590.0 | C26: ='Récap MEAUX II 2025'!E71 | D26: =B26*C26 | E26: =Paramètres!$J$9/365 | F26: =D26*E26
A27: Désenfumage | B27: =Paramètres!$C$9/38590.0 | C27: ='Récap MEAUX II 2025'!E74 | D27: =B27*C27 | E27: =Paramètres!$J$9/365 | F27: =D27*E27
A28: Espaces verts | B28: =Paramètres!$C$9/38590.0 | C28: ='Récap MEAUX II 2025'!E81 | D28: =B28*C28 | E28: =Paramètres!$J$9/365 | F28: =D28*E28
A29: Portails + Barrières automatiques | B29: =Paramètres!$C$9/38590.0 | C29: ='Récap MEAUX II 2025'!E84 | D29: =B29*C29 | E29: =Paramètres!$J$9/365 | F29: =D29*E29
A30: Portes Coupe-Feu | B30: =Paramètres!$C$9/38590.0 | C30: ='Récap MEAUX II 2025'!E87 | D30: =B30*C30 | E30: =Paramètres!$J$9/365 | F30: =D30*E30
A31: Protection foudre | B31: =Paramètres!$C$9/38590.0 | C31: ='Récap MEAUX II 2025'!E90 | D31: =B31*C31 | E31: =Paramètres!$J$9/365 | F31: =D31*E31
A32: Quais & Portes sectionnelles | B32: =Paramètres!$C$9/38590.0 | C32: ='Récap MEAUX II 2025'!E93 | D32: =B32*C32 | E32: =Paramètres!$J$9/365 | F32: =D32*E32
A33: Séparateur hydro. | B33: =Paramètres!$C$9/38590.0 | C33: ='Récap MEAUX II 2025'!E96 | D33: =B33*C33 | E33: =Paramètres!$J$9/365 | F33: =D33*E33
A34: Sprinklers - RIA - PI - Fioul | B34: =Paramètres!$C$9/38590.0 | C34: ='Récap MEAUX II 2025'!E102 | D34: =B34*C34 | E34: =Paramètres!$J$9/365 | F34: =D34*E34
A35: SSI | B35: =Paramètres!$C$9/38590.0 | C35: ='Récap MEAUX II 2025'!E105 | D35: =B35*C35 | E35: =Paramètres!$J$9/365 | F35: =D35*E35
A36: Télésurveillance | B36: =Paramètres!$C$9/38590.0 | C36: ='Récap MEAUX II 2025'!E119 | D36: =B36*C36 | E36: =Paramètres!$J$9/365 | F36: =D36*E36
A37: Toiture | B37: =Paramètres!$C$9/38590.0 | C37: ='Récap MEAUX II 2025'!E123 | D37: =B37*C37 | E37: =Paramètres!$J$9/365 | F37: =D37*E37
A38: Vérifications règlementaires | B38: =Paramètres!$C$9/38590.0 | C38: ='Récap MEAUX II 2025'!E127 | D38: =B38*C38 | E38: =Paramètres!$J$9/365 | F38: =D38*E38
A39: Sous-total — CONTRAT MAINTENANCE | C39: =SUM(C25:C38) | D39: =SUM(D25:D38) | F39: =SUM(F25:F38)
A40: TAXES
A41: Taxe Bureau & Stationnement | B41: =Paramètres!$C$9/38590.0 | C41: ='Récap MEAUX II 2025'!E132 | D41: =B41*C41 | E41: =Paramètres!$J$9/365 | F41: =D41*E41
A42: Sous-total — TAXES | C42: =SUM(C41:C41) | D42: =SUM(D41:D41) | F42: =SUM(F41:F41)
A45: TOTAL CHARGES RÉCUPÉRABLES RÉELLES (€ HT) | C45: =C9+C17+C20+C23+C39+C42 | D45: =D9+D17+D20+D23+D39+D42 | F45: =F9+F17+F20+F23+F39+F42
A47: Provisions pour charges versées | D47: Montant annuel (€) | F47: Montant locataire (€)
A48: 1er trimestre (T1)
A49: 2e trimestre (T2)
A50: 3e trimestre (T3)
A51: 4e trimestre (T4)
A52: Total provisions pour charges versées → | D52: =SUM(D48:D51) | F52: =SUM(F48:F51)
A54: =IF(F45-F52>0,"SOLDE DÉBITEUR","SOLDE CRÉDITEUR") | D54: =D45-D52 | F54: =F45-F52
A56: ℹ Clé répartition = surface lot ÷ surface totale site. Période = nombre de jours d'occupation ÷ 365.

Sheet C3
A1: RÉGULARISATION DE CHARGES — C3
A2: Site : MEAUX PN01 | Année 2025
A3: =Paramètres!$B$10&IF(Paramètres!$E$10<>""," — "&Paramètres!$E$10,"")
A4: Poste | B4: Clé répartition | C4: Total HT | D4: QP annuelle | E4: Période | F4: QP locataire
A5: CHARGES SITE — MEAUX PN01
A6: CONTRAT MAINTENANCE
A7: Portails + Barrières automatiques | B7: =Paramètres!$C$10/Paramètres!$C$3 | C7: ='Récap MEAUX II 2025'!E84 | D7: =B7*C7 | E7: =Paramètres!$J$10/365 | F7: =D7*E7
A8: Vérifications règlementaires | B8: =Paramètres!$C$10/Paramètres!$C$3 | C8: ='Récap MEAUX II 2025'!E127 | D8: =B8*C8 | E8: =Paramètres!$J$10/365 | F8: =D8*E8
A9: Sous-total — CONTRAT MAINTENANCE | C9: =SUM(C7:C8) | D9: =SUM(D7:D8) | F9: =SUM(F7:F8)
A11: CHARGES BÂTIMENT — MEAUX II
A12: FLUIDES
A13: Eau | B13: =Paramètres!$C$10/38590.0 | C13: ='Récap MEAUX II 2025'!E8 | D13: =B13*C13 | E13: =Paramètres!$H$10/365 | F13: =D13*E13
A14: Eau - Incendie | B14: =Paramètres!$C$10/38590.0 | C14: ='Récap MEAUX II 2025'!E12 | D14: =B14*C14 | E14: =Paramètres!$H$10/365 | F14: =D14*E14
A15: Electricité | B15: =Paramètres!$C$10/38590.0 | C15: ='Récap MEAUX II 2025'!E26 | D15: =B15*C15 | E15: =Paramètres!$H$10/365 | F15: =D15*E15
A16: Gaz | B16: =Paramètres!$C$10/38590.0 | C16: ='Récap MEAUX II 2025'!E40 | D16: =B16*C16 | E16: =Paramètres!$H$10/365 | F16: =D16*E16
A17: Sous-total — FLUIDES | C17: =SUM(C13:C16) | D17: =SUM(D13:D16) | F17: =SUM(F13:F16)
A18: HONORAIRES
A19: Honoraires Divers | B19: =Paramètres!$C$10/38590.0 | C19: ='Récap MEAUX II 2025'!E45 | D19: =B19*C19 | E19: =Paramètres!$J$10/365 | F19: =D19*E19
A20: Sous-total — HONORAIRES | C20: =SUM(C19:C19) | D20: =SUM(D19:D19) | F20: =SUM(F19:F19)
A21: TRAVAUX
A22: Entretien Courant | B22: =Paramètres!$C$10/38590.0 | C22: ='Récap MEAUX II 2025'!E63 | D22: =B22*C22 | E22: =Paramètres!$J$10/365 | F22: =D22*E22
A23: Sous-total — TRAVAUX | C23: =SUM(C22:C22) | D23: =SUM(D22:D22) | F23: =SUM(F22:F22)
A24: CONTRAT MAINTENANCE
A25: Ascenseur | B25: =Paramètres!$C$10/38590.0 | C25: ='Récap MEAUX II 2025'!E67 | D25: =B25*C25 | E25: =Paramètres!$J$10/365 | F25: =D25*E25
A26: Chaufferie | B26: =Paramètres!$C$10/38590.0 | C26: ='Récap MEAUX II 2025'!E71 | D26: =B26*C26 | E26: =Paramètres!$J$10/365 | F26: =D26*E26
A27: Désenfumage | B27: =Paramètres!$C$10/38590.0 | C27: ='Récap MEAUX II 2025'!E74 | D27: =B27*C27 | E27: =Paramètres!$J$10/365 | F27: =D27*E27
A28: Espaces verts | B28: =Paramètres!$C$10/38590.0 | C28: ='Récap MEAUX II 2025'!E81 | D28: =B28*C28 | E28: =Paramètres!$J$10/365 | F28: =D28*E28
A29: Portails + Barrières automatiques | B29: =Paramètres!$C$10/38590.0 | C29: ='Récap MEAUX II 2025'!E84 | D29: =B29*C29 | E29: =Paramètres!$J$10/365 | F29: =D29*E29
A30: Portes Coupe-Feu | B30: =Paramètres!$C$10/38590.0 | C30: ='Récap MEAUX II 2025'!E87 | D30: =B30*C30 | E30: =Paramètres!$J$10/365 | F30: =D30*E30
A31: Protection foudre | B31: =Paramètres!$C$10/38590.0 | C31: ='Récap MEAUX II 2025'!E90 | D31: =B31*C31 | E31: =Paramètres!$J$10/365 | F31: =D31*E31
A32: Quais & Portes sectionnelles | B32: =Paramètres!$C$10/38590.0 | C32: ='Récap MEAUX II 2025'!E93 | D32: =B32*C32 | E32: =Paramètres!$J$10/365 | F32: =D32*E32
A33: Séparateur hydro. | B33: =Paramètres!$C$10/38590.0 | C33: ='Récap MEAUX II 2025'!E96 | D33: =B33*C33 | E33: =Paramètres!$J$10/365 | F33: =D33*E33
A34: Sprinklers - RIA - PI - Fioul | B34: =Paramètres!$C$10/38590.0 | C34: ='Récap MEAUX II 2025'!E102 | D34: =B34*C34 | E34: =Paramètres!$J$10/365 | F34: =D34*E34
A35: SSI | B35: =Paramètres!$C$10/38590.0 | C35: ='Récap MEAUX II 2025'!E105 | D35: =B35*C35 | E35: =Paramètres!$J$10/365 | F35: =D35*E35
A36: Télésurveillance | B36: =Paramètres!$C$10/38590.0 | C36: ='Récap MEAUX II 2025'!E119 | D36: =B36*C36 | E36: =Paramètres!$J$10/365 | F36: =D36*E36
A37: Toiture | B37: =Paramètres!$C$10/38590.0 | C37: ='Récap MEAUX II 2025'!E123 | D37: =B37*C37 | E37: =Paramètres!$J$10/365 | F37: =D37*E37
A38: Vérifications règlementaires | B38: =Paramètres!$C$10/38590.0 | C38: ='Récap MEAUX II 2025'!E127 | D38: =B38*C38 | E38: =Paramètres!$J$10/365 | F38: =D38*E38
A39: Sous-total — CONTRAT MAINTENANCE | C39: =SUM(C25:C38) | D39: =SUM(D25:D38) | F39: =SUM(F25:F38)
A40: TAXES
A41: Taxe Bureau & Stationnement | B41: =Paramètres!$C$10/38590.0 | C41: ='Récap MEAUX II 2025'!E132 | D41: =B41*C41 | E41: =Paramètres!$J$10/365 | F41: =D41*E41
A42: Sous-total — TAXES | C42: =SUM(C41:C41) | D42: =SUM(D41:D41) | F42: =SUM(F41:F41)
A45: TOTAL CHARGES RÉCUPÉRABLES RÉELLES (€ HT) | C45: =C9+C17+C20+C23+C39+C42 | D45: =D9+D17+D20+D23+D39+D42 | F45: =F9+F17+F20+F23+F39+F42
A47: Provisions pour charges versées | D47: Montant annuel (€) | F47: Montant locataire (€)
A48: 1er trimestre (T1)
A49: 2e trimestre (T2)
A50: 3e trimestre (T3)
A51: 4e trimestre (T4)
A52: Total provisions pour charges versées → | D52: =SUM(D48:D51) | F52: =SUM(F48:F51)
A54: =IF(F45-F52>0,"SOLDE DÉBITEUR","SOLDE CRÉDITEUR") | D54: =D45-D52 | F54: =F45-F52
A56: ℹ Clé répartition = surface lot ÷ surface totale site. Période = nombre de jours d'occupation ÷ 365.

Sheet C4
A1: RÉGULARISATION DE CHARGES — C4
A2: Site : MEAUX PN01 | Année 2025
A3: =Paramètres!$B$11&IF(Paramètres!$E$11<>""," — "&Paramètres!$E$11,"")
A4: Poste | B4: Clé répartition | C4: Total HT | D4: QP annuelle | E4: Période | F4: QP locataire
A5: CHARGES SITE — MEAUX PN01
A6: CONTRAT MAINTENANCE
A7: Portails + Barrières automatiques | B7: =Paramètres!$C$11/Paramètres!$C$3 | C7: ='Récap MEAUX II 2025'!E84 | D7: =B7*C7 | E7: =Paramètres!$J$11/365 | F7: =D7*E7
A8: Vérifications règlementaires | B8: =Paramètres!$C$11/Paramètres!$C$3 | C8: ='Récap MEAUX II 2025'!E127 | D8: =B8*C8 | E8: =Paramètres!$J$11/365 | F8: =D8*E8
A9: Sous-total — CONTRAT MAINTENANCE | C9: =SUM(C7:C8) | D9: =SUM(D7:D8) | F9: =SUM(F7:F8)
A11: CHARGES BÂTIMENT — MEAUX II
A12: FLUIDES
A13: Eau | B13: =Paramètres!$C$11/38590.0 | C13: ='Récap MEAUX II 2025'!E8 | D13: =B13*C13 | E13: =Paramètres!$H$11/365 | F13: =D13*E13
A14: Eau - Incendie | B14: =Paramètres!$C$11/38590.0 | C14: ='Récap MEAUX II 2025'!E12 | D14: =B14*C14 | E14: =Paramètres!$H$11/365 | F14: =D14*E14
A15: Electricité | B15: =Paramètres!$C$11/38590.0 | C15: ='Récap MEAUX II 2025'!E26 | D15: =B15*C15 | E15: =Paramètres!$H$11/365 | F15: =D15*E15
A16: Gaz | B16: =Paramètres!$C$11/38590.0 | C16: ='Récap MEAUX II 2025'!E40 | D16: =B16*C16 | E16: =Paramètres!$H$11/365 | F16: =D16*E16
A17: Sous-total — FLUIDES | C17: =SUM(C13:C16) | D17: =SUM(D13:D16) | F17: =SUM(F13:F16)
A18: HONORAIRES
A19: Honoraires Divers | B19: =Paramètres!$C$11/38590.0 | C19: ='Récap MEAUX II 2025'!E45 | D19: =B19*C19 | E19: =Paramètres!$J$11/365 | F19: =D19*E19
A20: Sous-total — HONORAIRES | C20: =SUM(C19:C19) | D20: =SUM(D19:D19) | F20: =SUM(F19:F19)
A21: TRAVAUX
A22: Entretien Courant | B22: =Paramètres!$C$11/38590.0 | C22: ='Récap MEAUX II 2025'!E63 | D22: =B22*C22 | E22: =Paramètres!$J$11/365 | F22: =D22*E22
A23: Sous-total — TRAVAUX | C23: =SUM(C22:C22) | D23: =SUM(D22:D22) | F23: =SUM(F22:F22)
A24: CONTRAT MAINTENANCE
A25: Ascenseur | B25: =Paramètres!$C$11/38590.0 | C25: ='Récap MEAUX II 2025'!E67 | D25: =B25*C25 | E25: =Paramètres!$J$11/365 | F25: =D25*E25
A26: Chaufferie | B26: =Paramètres!$C$11/38590.0 | C26: ='Récap MEAUX II 2025'!E71 | D26: =B26*C26 | E26: =Paramètres!$J$11/365 | F26: =D26*E26
A27: Désenfumage | B27: =Paramètres!$C$11/38590.0 | C27: ='Récap MEAUX II 2025'!E74 | D27: =B27*C27 | E27: =Paramètres!$J$11/365 | F27: =D27*E27
A28: Espaces verts | B28: =Paramètres!$C$11/38590.0 | C28: ='Récap MEAUX II 2025'!E81 | D28: =B28*C28 | E28: =Paramètres!$J$11/365 | F28: =D28*E28
A29: Portails + Barrières automatiques | B29: =Paramètres!$C$11/38590.0 | C29: ='Récap MEAUX II 2025'!E84 | D29: =B29*C29 | E29: =Paramètres!$J$11/365 | F29: =D29*E29
A30: Portes Coupe-Feu | B30: =Paramètres!$C$11/38590.0 | C30: ='Récap MEAUX II 2025'!E87 | D30: =B30*C30 | E30: =Paramètres!$J$11/365 | F30: =D30*E30
A31: Protection foudre | B31: =Paramètres!$C$11/38590.0 | C31: ='Récap MEAUX II 2025'!E90 | D31: =B31*C31 | E31: =Paramètres!$J$11/365 | F31: =D31*E31
A32: Quais & Portes sectionnelles | B32: =Paramètres!$C$11/38590.0 | C32: ='Récap MEAUX II 2025'!E93 | D32: =B32*C32 | E32: =Paramètres!$J$11/365 | F32: =D32*E32
A33: Séparateur hydro. | B33: =Paramètres!$C$11/38590.0 | C33: ='Récap MEAUX II 2025'!E96 | D33: =B33*C33 | E33: =Paramètres!$J$11/365 | F33: =D33*E33
A34: Sprinklers - RIA - PI - Fioul | B34: =Paramètres!$C$11/38590.0 | C34: ='Récap MEAUX II 2025'!E102 | D34: =B34*C34 | E34: =Paramètres!$J$11/365 | F34: =D34*E34
A35: SSI | B35: =Paramètres!$C$11/38590.0 | C35: ='Récap MEAUX II 2025'!E105 | D35: =B35*C35 | E35: =Paramètres!$J$11/365 | F35: =D35*E35
A36: Télésurveillance | B36: =Paramètres!$C$11/38590.0 | C36: ='Récap MEAUX II 2025'!E119 | D36: =B36*C36 | E36: =Paramètres!$J$11/365 | F36: =D36*E36
A37: Toiture | B37: =Paramètres!$C$11/38590.0 | C37: ='Récap MEAUX II 2025'!E123 | D37: =B37*C37 | E37: =Paramètres!$J$11/365 | F37: =D37*E37
A38: Vérifications règlementaires | B38: =Paramètres!$C$11/38590.0 | C38: ='Récap MEAUX II 2025'!E127 | D38: =B38*C38 | E38: =Paramètres!$J$11/365 | F38: =D38*E38
A39: Sous-total — CONTRAT MAINTENANCE | C39: =SUM(C25:C38) | D39: =SUM(D25:D38) | F39: =SUM(F25:F38)
A40: TAXES
A41: Taxe Bureau & Stationnement | B41: =Paramètres!$C$11/38590.0 | C41: ='Récap MEAUX II 2025'!E132 | D41: =B41*C41 | E41: =Paramètres!$J$11/365 | F41: =D41*E41
A42: Sous-total — TAXES | C42: =SUM(C41:C41) | D42: =SUM(D41:D41) | F42: =SUM(F41:F41)
A45: TOTAL CHARGES RÉCUPÉRABLES RÉELLES (€ HT) | C45: =C9+C17+C20+C23+C39+C42 | D45: =D9+D17+D20+D23+D39+D42 | F45: =F9+F17+F20+F23+F39+F42
A47: Provisions pour charges versées | D47: Montant annuel (€) | F47: Montant locataire (€)
A48: 1er trimestre (T1)
A49: 2e trimestre (T2)
A50: 3e trimestre (T3)
A51: 4e trimestre (T4)
A52: Total provisions pour charges versées → | D52: =SUM(D48:D51) | F52: =SUM(F48:F51)
A54: =IF(F45-F52>0,"SOLDE DÉBITEUR","SOLDE CRÉDITEUR") | D54: =D45-D52 | F54: =F45-F52
A56: ℹ Clé répartition = surface lot ÷ surface totale site. Période = nombre de jours d'occupation ÷ 365.

Sheet Vacance Locative
A1: MEAUX PN01 — COÛT DE LA VACANCE LOCATIVE 2025
A2: Estimation de la perte de charges non récupérées sur les lots vacants
A4: Lot | B4: Statut | C4: Surface (m²) | D4: QP annuelle (€ HT) | E4: Période (j/365) | F4: Coût vacance (€ HT)
A5: =Paramètres!A7 | B5: =Paramètres!B7 | C5: =Paramètres!C7 | D5: ='BAT 1 - MEAUX I'!D27 | E5: =Paramètres!H7/365 | F5: =IF(Paramètres!B7="Vacant",'BAT 1 - MEAUX I'!D27,'BAT 1 - MEAUX I'!D27-'BAT 1 - MEAUX I'!F27)
A6: =Paramètres!A8 | B6: =Paramètres!B8 | C6: =Paramètres!C8 | D6: ='C1'!D45 | E6: =Paramètres!H8/365 | F6: =IF(Paramètres!B8="Vacant",'C1'!D45,'C1'!D45-'C1'!F45)
A7: =Paramètres!A9 | B7: =Paramètres!B9 | C7: =Paramètres!C9 | D7: ='C2'!D45 | E7: =Paramètres!H9/365 | F7: =IF(Paramètres!B9="Vacant",'C2'!D45,'C2'!D45-'C2'!F45)
A8: =Paramètres!A10 | B8: =Paramètres!B10 | C8: =Paramètres!C10 | D8: ='C3'!D45 | E8: =Paramètres!H10/365 | F8: =IF(Paramètres!B10="Vacant",'C3'!D45,'C3'!D45-'C3'!F45)
A9: =Paramètres!A11 | B9: =Paramètres!B11 | C9: =Paramètres!C11 | D9: ='C4'!D45 | E9: =Paramètres!H11/365 | F9: =IF(Paramètres!B11="Vacant",'C4'!D45,'C4'!D45-'C4'!F45)
A11: Total QP charges (tous lots) | D11: =SUM(D5:D9)
A12: Nombre de lots vacants | D12: =COUNTIF(B5:B9,"Vacant")
A14: Charges non récupérables (Frais Bancaires + CAPEX) | F14: ='Récap Site 2025'!E22
A16: TOTAL COÛT DE LA VACANCE LOCATIVE (€ HT) | F16: =F5+F6+F7+F8+F9+F14
A18: Part vacance sur total charges site | F18: =IF(D11>0,F16/D11,0)
A20: ℹ QP annuelle = Total site HT × clé de répartition. Coût vacance = QP annuelle × fraction de l'année non occupée.
