Workbook

Sheet Récapitulatif 2025
A1: ORMES A — RÉCAPITULATIF DES CHARGES 2025
A2: Site : ORMES A | Période : 01/01/2025 – 31/12/2025
A3: Fournisseur | B3: Date facture | C3: N° facture | D3: Description | E3: Montant HT (€) | F3: TVA (€) | G3: Montant TTC (€)
A4: ── FLUIDES ──
A5: Eau
A6: AQUALIGE | C6: 1096904376-1 | D6: Mise en service | E6: 49.82 | F6: 4.98 | G6: 54.8
A7: AQUALIGE | C7: 1096892743-1 | D7: Mise en service | E7: 49.82 | F7: 4.98 | G7: 54.8
A8: AQUALIGE | B8: 45854 | C8: 1099190061 | D8: EAU ET ASSAINISSEMENT COMPTEUR 124MK046246 | E8: 645.02 | F8: 46.22 | G8: 691.24
A9: AQUALIGE | B9: 45854 | C9: 1099203459 | D9: EAU ET ASSAINISSEMENT COMPTEUR C24FE015783 | E9: 292.74 | F9: 21.75 | G9: 314.49
A10: Sous-total — Eau | E10: =SUM(E6:E9) | F10: =SUM(F6:F9) | G10: =SUM(G6:G9)
A11: Electricité
A12: ENGIE | B12: 45780 | C12: 1200009625875 | D12: CONSOMMATIONS ELECTRICITE 01/04/2025 au 30/04/2025 | E12: 4337.28 | F12: 867.46 | G12: 5204.74
A13: ENGIE | B13: 45813 | C13: 40017044367 | D13: CONSOMMATIONS ELECTRICTITE | E13: 3646.51 | F13: 729.3 | G13: 4375.81
A14: ENGIE | B14: 45843 | C14: 520002087186 | D14: CONSOMMATIONS ELECTRICTITE | E14: 3379.85 | F14: 675.97 | G14: 4055.82
A15: ENGIE | B15: 45876 | C15: 320007792334 | D15: CONSOMMATIONS ELECTRICTITE | E15: 3600.2 | F15: 720.04 | G15: 4320.24
A16: ENGIE | B16: 45904 | C16: 760000335269 | D16: CONSOMMATIONS ELECTRICTITE | E16: 3715.72 | F16: 743.14 | G16: 4458.86
A17: ENGIE | B17: 45934 | C17: 630000369535 | D17: CONSOMMATIONS ELECTRICTITE | E17: 3737.12 | F17: 747.42 | G17: 4484.54
A18: ENGIE | B18: 45965 | C18: 690000378639 | D18: CONSOMMATIONS ELECTRICTITE | E18: 4184.89 | F18: 836.98 | G18: 5021.87
A19: ENGIE | B19: 45995 | C19: 670000394240 | D19: CONSOMMATIONS ELECTRICTITE | E19: 6650.18 | F19: 1330.04 | G19: 7980.22
A20: ENGIE | B20: 46025 | C20: 980006173374 | D20: CONSOMMATIONS ELECTRICTITE | E20: 7445.64 | F20: 1489.13 | G20: 8934.77
A21: Sous-total — Electricité | E21: =SUM(E12:E20) | F21: =SUM(F12:F20) | G21: =SUM(G12:G20)
A22: Gaz
A23: ENGIE | B23: 45782 | C23: 680000258800 | D23: CONSOMMATIONS GAZ 02/04/2025 au 01/05/2025 | E23: 2147.53 | F23: 160.14 | G23: 2307.67
A24: ENGIE | B24: 45813 | C24: 780000262507 | D24: CONSOMMATIONS GAZ | E24: 2039.74 | F24: 125.43 | G24: 2165.17
A25: ENGIE | B25: 45842 | C25: 820001240297 | D25: CONSOMMATIONS GAZ | E25: 2039.74 | F25: 125.43 | G25: 2165.17
A26: ENGIE | B26: 45873 | C26: 40017074775 | D26: CONSOMMATIONS GAZ | E26: 2048.67 | F26: 126.15 | G26: 2174.82
A27: ENGIE | B27: 45904 | C27: 65000032141 | D27: CONSOMMATIONS GAZ | E27: 2048.67 | F27: 409.73 | G27: 2458.4
A28: ENGIE | B28: 45934 | C28: 420006908243 | D28: CONSOMMATIONS GAZ | E28: 2048.67 | F28: 409.73 | G28: 2458.4
A29: ENGIE | B29: 45966 | C29: 690000380305 | D29: CONSOMMATIONS GAZ | E29: 2049.48 | F29: 409.9 | G29: 2459.38
A30: ENGIE | B30: 45995 | C30: 820006290113 | D30: CONSOMMATIONS GAZ | E30: 2055.74 | F30: 411.15 | G30: 2466.89
A31: ENGIE | B31: 46026 | C31: 20040377238 | D31: CONSOMMATIONS GAZ | E31: 2063.48 | F31: 412.7 | G31: 2476.18
A32: Sous-total — Gaz | E32: =SUM(E23:E31) | F32: =SUM(F23:F31) | G32: =SUM(G23:G31)
A33: ── TRAVAUX ──
A34: Entretien Courant
A35: ESPACE CLOTURE CENTRE | B35: 45803 | C35: 18011749 | D35: INSTALLATION BOUCLE SORTIE SUR PORTAIL VL | E35: 610 | F35: 122 | G35: 732
A36: ESPACE CLOTURE CENTRE | B36: 45832 | C36: 18011816 | D36: POSE DIGICODE | E36: 734.4 | F36: 146.88 | G36: 881.28
A37: Sous-total — Entretien Courant | E37: =SUM(E35:E36) | F37: =SUM(F35:F36) | G37: =SUM(G35:G36)
A38: ── CONTRAT MAINTENANCE ──
A39: Espaces Verts
A40: ARP ASTRANCE | B40: 45838 | C40: FC-ARP-25-06-0141 | D40: Suivis écologiques | E40: 1500 | F40: 300 | G40: 1800
A41: ARP ASTRANCE | B41: 45869 | C41: FC-ARP-25-07-0086 | D41: Suivis écologiques | E41: 2250 | F41: 450 | G41: 2700
A42: BOURDIN | B42: 45894 | C42: BP25080709 | D42: Entretien espaces verts | E42: 1777.5 | F42: 355.5 | G42: 2133
A43: ARP ASTRANCE | B43: 45991 | C43: FC-ARP-25-11-0060 | D43: Suivis écologiques | E43: 2450 | F43: 490 | G43: 2940
A44: BOURDIN | B44: 45986 | C44: BP 9000870 | D44: Entretien espaces verts | E44: 1777.5 | F44: 355.5 | G44: 2133
A45: ARP.Astrance | B45: 45961 | C45: FC-ARP-25-10-0205 | D45: Mission d'assistance à maîtrise d'ouvrage pour la réalisation de suivi écologiques | E45: 562.5 | F45: 112.5 | G45: 675
A46: Sous-total — Espaces Verts | E46: =SUM(E40:E45) | F46: =SUM(F40:F45) | G46: =SUM(G40:G45)
A47: CVC
A48: EIFFAGE | B48: 45841 | C48: F00190250700001 | D48: MAINTENANCE CVC CHAUFFERIE CLIMATISATION VRD PLOMBERIE | E48: 3430 | F48: 686 | G48: 4116
A49: EIFFAGE | B49: 45988 | C49: F00190251100472 | D49: REGULARISATION DEFAUT POMPE DE RELEVAGE | E49: 250 | F49: 50 | G49: 300
A50: Sous-total — CVC | E50: =SUM(E48:E49) | F50: =SUM(F48:F49) | G50: =SUM(G48:G49)
A51: Sécurité
A52: AVC Sécurité | B52: 45776 | D52: CONTRAT DE TELESURVEILLANCE + GSM | E52: 840 | F52: 168 | G52: 1008
A53: AVC Sécurité | B53: 45747 | D53: CONTRAT DE TELESURVEILLANCE + GSM | E53: 840 | F53: 168 | G53: 1008
A54: Sous-total — Sécurité | E54: =SUM(E52:E53) | F54: =SUM(F52:F53) | G54: =SUM(G52:G53)
A55: SSI
A56: CONCEPT SECURITE | B56: 45832 | C56: FA022398 | D56: DEPANNAGE SSI - EXERCICE ID LOGISTICS | E56: 304 | F56: 60.8 | G56: 364.8
A57: CONCEPT SECURITE | B57: 45929 | C57: FA022971 | D57: Fourniture des pose des extincteurs parties communes | E57: 922.07 | F57: 184.41 | G57: 1106.48
A58: CONCEPT SECURITE | B58: 45936 | C58: FA023051 | D58: Dépannage porte coupe-feu et porte piétonne | E58: 194 | F58: 38.8 | G58: 232.8
A59: Sous-total — SSI | E59: =SUM(E56:E58) | F59: =SUM(F56:F58) | G59: =SUM(G56:G58)
A60: Toitures
A61: SIPHOTEC | B61: 45838 | C61: FE2506737 | D61: ENTRETIEN SIPHOÏDES | E61: 2600 | F61: 520 | G61: 3120
A62: SIPHOTEC | B62: 45961 | C62: FE2510768 | D62: ENTRETIEN DU SYSTÈME SIPHOIDE | E62: 2600 | F62: 520 | G62: 3120
A63: PROTECTA | B63: 46014 | C63: FA-45-2025-0564 | D63: VISITE TOITURE / RAPPORT PHOTO | E63: 1125.66 | F63: 225.13 | G63: 1350.79
A64: Sous-total — Toitures | E64: =SUM(E61:E63) | F64: =SUM(F61:F63) | G64: =SUM(G61:G63)
A65: SPK / RIA / PI
A66: AXIMA | B66: 45750 | C66: 8710250910 | D66: CONTRAT D’ENTRETIEN DE PROTECTION INCENDIE du 21/03/25 au 20/04/25 | E66: 2224.33 | F66: 444.87 | G66: 2669.2
A67: AXIMA | B67: 45768 | C67: 8710250911 | D67: CONTRAT D’ENTRETIEN DE PROTECTION INCENDIE du 21/04/25 au 20/05/25 | E67: 2224.33 | F67: 444.87 | G67: 2669.2
A68: AXIMA | B68: 45798 | C68: 8710252246 | D68: ENTRETIEN PROTECTION INCENDIE | E68: 2224.33 | F68: 444.87 | G68: 2669.2
A69: AXIMA | B69: 45829 | C69: 8710253747 | D69: ENTRETIEN PROTECTION INCENDIE | E69: 2224.33 | F69: 444.87 | G69: 2669.2
A70: AXIMA | B70: 45864 | C70: 8710255568 | D70: ENTRETIEN PROTECTION INCENDIE | E70: 2224.33 | F70: 444.87 | G70: 2669.2
A71: AXIMA | B71: 45870 | C71: 8710257942 | D71: Fourniture de gasoil - protection incendie | E71: 2656.4 | F71: 531.28 | G71: 3187.68
A72: AXIMA | B72: 45890 | C72: 8710257717 | D72: ENTRETIEN PROTECTION INCENDIE | E72: 2224.33 | F72: 444.87 | G72: 2669.2
A73: AXIMA | B73: 45921 | C73: 8710259036 | D73: ENTRETIEN PROTECTION INCENDIE | E73: 2224.33 | F73: 444.87 | G73: 2669.2
A74: AXIMA | B74: 45951 | C74: 8710260974 | D74: ENTRETIEN PROTECTION INCENDIE | E74: 2224.33 | F74: 444.87 | G74: 2669.2
A75: AXIMA | B75: 45982 | C75: 8710262855 | D75: ENTRETIEN PROTECTION INCENDIE | E75: 2224.33 | F75: 444.87 | G75: 2669.2
A76: AXIMA | B76: 46012 | C76: 8710264942 | D76: CONTRAT D’ENTRETIEN DE PROTECTION INCENDIE du 21/12/25 au 20/01/26 | E76: 2224.33 | F76: 444.87 | G76: 2669.2
A77: Sous-total — SPK / RIA / PI | E77: =SUM(E66:E76) | F77: =SUM(F66:F76) | G77: =SUM(G66:G76)
A78: Installations électriques
A79: OTIS | B79: 45833 | C79: VOF 8192916 | D79: MAINTENANCE ASCENSEURS MAI JUIN 25 | E79: 500 | F79: 100 | G79: 600
A80: OTIS | B80: 45841 | C80: VOF 8251287 | D80: MAINTENANCE ASCENSEURS T3 | E80: 750 | F80: 150 | G80: 900
A81: EIFFAGE | B81: 45833 | C81: F00190250600306 | D81: Maintenance électricité | E81: 4700 | F81: 940 | G81: 5640
A82: OTIS | B82: 45932 | C82: VOF 8380322 | D82: Prestations de services Entretien du 01/10/25 au 31/12/25-Ascenceur | E82: 750 | F82: 150 | G82: 900
A83: Sous-total — Installations électriques | E83: =SUM(E79:E82) | F83: =SUM(F79:F82) | G83: =SUM(G79:G82)
A84: Protection Foudre
A85: Etablissement Renard | B85: 46006 | C85: 2512205 | D85: Contrat de vérification-maintenance protection contre la foudre | E85: 1920 | F85: 384 | G85: 2304
A86: BUREAU VERITAS | E86: 695 | F86: 139 | G86: 834
A87: BUREAU VERITAS | B87: 45918 | C87: 25546933 | D87: Vérification périodique des installations électriques (Q19) | E87: 695 | F87: 139 | G87: 834
A88: Sous-total — Protection Foudre | E88: =SUM(E85:E87) | F88: =SUM(F85:F87) | G88: =SUM(G85:G87)
A89: GTB
A90: CN 45 | E90: 514 | F90: 102.8 | G90: 616.8
A91: CN 45 | B91: 45835 | C91: 2025/754 | E91: 514 | F91: 102.8 | G91: 616.8
A92: SOA | E92: 2577 | F92: 515.4 | G92: 3092.4
A93: SOA | B93: 45956 | C93: 251003937 | D93: Entretien des séparateurs hydrocarbures | E93: 2577 | F93: 515.4 | G93: 3092.4
A94: NEO DB / B27 / BUREAU VERITAS | E94: 1602.5 | F94: 320.5 | G94: 1923
A95: BUREAU VERITAS | B95: 45859 | C95: 25425847 | D95: CONTRÔLE REJETS CHAUFFERIE ET REJETS ACQUEUX | E95: 1147.5 | F95: 229.5 | G95: 1377
A96: BUREAU VERITAS | B96: 45918 | D96: Vérification périodique des disconnecteurs | E96: 455 | F96: 91 | G96: 546
A97: Sous-total — GTB | E97: =SUM(E90:E96) | F97: =SUM(F90:F96) | G97: =SUM(G90:G96)
A98: Détection Gaz
A99: BE ATEX | C99: CC65197 | D99: CONTRÔLE ET VERIFICATION DES EQUIPEMENTS DE DETECTION GAZ FIXES | E99: 344.96 | F99: 68.99 | G99: 413.95
A100: BE ATEX | B100: 45974 | C100: FC76885 | D100: CONTRÔLE ET VERIFICATION DES EQUIPEMENTS DE DETECTION GAZ FIXES | E100: 344.96 | F100: 68.99 | G100: 413.95
...

Sheet Paramètres
A1: ORMES A — PARAMÈTRES SITE 2025
A2: Site | C2: ORMES A
A3: Surface totale site (m²) | C3: 29565.91
A4: Année | C4: 2025
A6: Lot | B6: Statut | C6: Surface (m²) | D6: Bâtiment | E6: Locataire | F6: Début de bail | G6: Fin de bail | H6: Jours 2025 | I6: Prorata
A7: C1 C2 | B7: Occupé | C7: 9623 | E7: ID LOGISTICS | F7: 45737 | G7: 50119 | H7: =MAX(0,MIN(DATE(2025,12,31),IF(G7="",DATE(2025,12,31),G7))-MAX(DATE(2025,1,1),IF(F7="",DATE(2025,1,1),F7))+1) | I7: =H7/365
A8: C3 C4 C5 | B8: Vacant | C8: 19942.91 | H8: =MAX(0,MIN(DATE(2025,12,31),IF(G8="",DATE(2025,12,31),G8))-MAX(DATE(2025,1,1),IF(F8="",DATE(2025,1,1),F8))+1) | I8: =H8/365
A10: Poste (lié au Récapitulatif) | C10: Montant HT (€)
A11: =IFERROR(MID('Récapitulatif 2025'!A10,FIND(" — ",'Récapitulatif 2025'!A10)+4,100),"") | C11: ='Récapitulatif 2025'!E10
A12: =IFERROR(MID('Récapitulatif 2025'!A21,FIND(" — ",'Récapitulatif 2025'!A21)+4,100),"") | C12: ='Récapitulatif 2025'!E21
A13: =IFERROR(MID('Récapitulatif 2025'!A32,FIND(" — ",'Récapitulatif 2025'!A32)+4,100),"") | C13: ='Récapitulatif 2025'!E32
A14: =IFERROR(MID('Récapitulatif 2025'!A37,FIND(" — ",'Récapitulatif 2025'!A37)+4,100),"") | C14: ='Récapitulatif 2025'!E37
A15: =IFERROR(MID('Récapitulatif 2025'!A46,FIND(" — ",'Récapitulatif 2025'!A46)+4,100),"") | C15: ='Récapitulatif 2025'!E46
A16: =IFERROR(MID('Récapitulatif 2025'!A50,FIND(" — ",'Récapitulatif 2025'!A50)+4,100),"") | C16: ='Récapitulatif 2025'!E50
A17: =IFERROR(MID('Récapitulatif 2025'!A54,FIND(" — ",'Récapitulatif 2025'!A54)+4,100),"") | C17: ='Récapitulatif 2025'!E54
A18: =IFERROR(MID('Récapitulatif 2025'!A59,FIND(" — ",'Récapitulatif 2025'!A59)+4,100),"") | C18: ='Récapitulatif 2025'!E59
A19: =IFERROR(MID('Récapitulatif 2025'!A64,FIND(" — ",'Récapitulatif 2025'!A64)+4,100),"") | C19: ='Récapitulatif 2025'!E64
A20: =IFERROR(MID('Récapitulatif 2025'!A77,FIND(" — ",'Récapitulatif 2025'!A77)+4,100),"") | C20: ='Récapitulatif 2025'!E77
A21: =IFERROR(MID('Récapitulatif 2025'!A83,FIND(" — ",'Récapitulatif 2025'!A83)+4,100),"") | C21: ='Récapitulatif 2025'!E83
A22: =IFERROR(MID('Récapitulatif 2025'!A88,FIND(" — ",'Récapitulatif 2025'!A88)+4,100),"") | C22: ='Récapitulatif 2025'!E88
A23: =IFERROR(MID('Récapitulatif 2025'!A97,FIND(" — ",'Récapitulatif 2025'!A97)+4,100),"") | C23: ='Récapitulatif 2025'!E97
A24: =IFERROR(MID('Récapitulatif 2025'!A101,FIND(" — ",'Récapitulatif 2025'!A101)+4,100),"") | C24: ='Récapitulatif 2025'!E101
A25: =IFERROR(MID('Récapitulatif 2025'!A104,FIND(" — ",'Récapitulatif 2025'!A104)+4,100),"") | C25: ='Récapitulatif 2025'!E104
A26: =IFERROR(MID('Récapitulatif 2025'!A107,FIND(" — ",'Récapitulatif 2025'!A107)+4,100),"") | C26: ='Récapitulatif 2025'!E107
A27: =IFERROR(MID('Récapitulatif 2025'!A111,FIND(" — ",'Récapitulatif 2025'!A111)+4,100),"") | C27: ='Récapitulatif 2025'!E111
A28: =IFERROR(MID('Récapitulatif 2025'!A118,FIND(" — ",'Récapitulatif 2025'!A118)+4,100),"") | C28: ='Récapitulatif 2025'!E118

Sheet C1 C2
A1: RÉGULARISATION DE CHARGES — C1 C2
A2: Site : ORMES A | Année 2025
A3: =Paramètres!$B$7&IF(Paramètres!$E$7<>""," — "&Paramètres!$E$7,"")
A4: Poste | B4: Clé répartition | C4: Total site HT | D4: QP annuelle | E4: Période | F4: QP locataire
A5: FLUIDES
A6: Eau | B6: =Paramètres!$C$7/Paramètres!$C$3 | C6: ='Récapitulatif 2025'!E10 | D6: =B6*C6 | E6: =Paramètres!$H$7/365 | F6: =D6*E6
A7: Electricité | B7: =Paramètres!$C$7/Paramètres!$C$3 | C7: ='Récapitulatif 2025'!E21 | D7: =B7*C7 | E7: =Paramètres!$H$7/365 | F7: =D7*E7
A8: Gaz | B8: =Paramètres!$C$7/Paramètres!$C$3 | C8: ='Récapitulatif 2025'!E32 | D8: =B8*C8 | E8: =Paramètres!$H$7/365 | F8: =D8*E8
A9: Sous-total — FLUIDES | C9: =SUM(C6:C8) | D9: =SUM(D6:D8) | F9: =SUM(F6:F8)
A10: TRAVAUX
A11: Entretien Courant | B11: =Paramètres!$C$7/Paramètres!$C$3 | C11: ='Récapitulatif 2025'!E37 | D11: =B11*C11 | E11: =Paramètres!$H$7/365 | F11: =D11*E11
A12: Sous-total — TRAVAUX | C12: =SUM(C11:C11) | D12: =SUM(D11:D11) | F12: =SUM(F11:F11)
A13: CONTRAT MAINTENANCE
A14: Espaces Verts | B14: =Paramètres!$C$7/Paramètres!$C$3 | C14: ='Récapitulatif 2025'!E46 | D14: =B14*C14 | E14: =Paramètres!$H$7/365 | F14: =D14*E14
A15: CVC | B15: =Paramètres!$C$7/Paramètres!$C$3 | C15: ='Récapitulatif 2025'!E50 | D15: =B15*C15 | E15: =Paramètres!$H$7/365 | F15: =D15*E15
A16: Sécurité | B16: =Paramètres!$C$7/Paramètres!$C$3 | C16: ='Récapitulatif 2025'!E54 | D16: =B16*C16 | E16: =Paramètres!$H$7/365 | F16: =D16*E16
A17: SSI | B17: =Paramètres!$C$7/Paramètres!$C$3 | C17: ='Récapitulatif 2025'!E59 | D17: =B17*C17 | E17: =Paramètres!$H$7/365 | F17: =D17*E17
A18: Toitures | B18: =Paramètres!$C$7/Paramètres!$C$3 | C18: ='Récapitulatif 2025'!E64 | D18: =B18*C18 | E18: =Paramètres!$H$7/365 | F18: =D18*E18
A19: SPK / RIA / PI | B19: =Paramètres!$C$7/Paramètres!$C$3 | C19: ='Récapitulatif 2025'!E77 | D19: =B19*C19 | E19: =Paramètres!$H$7/365 | F19: =D19*E19
A20: Installations électriques | B20: =Paramètres!$C$7/35730.0 | C20: ='Récapitulatif 2025'!E83 | D20: =B20*C20 | E20: =Paramètres!$H$7/365 | F20: =D20*E20
A21: Protection Foudre | B21: =Paramètres!$C$7/23820.0 | C21: ='Récapitulatif 2025'!E88 | D21: =B21*C21 | E21: =Paramètres!$H$7/365 | F21: =D21*E21
A22: GTB | B22: =Paramètres!$C$7/Paramètres!$C$3 | C22: ='Récapitulatif 2025'!E97 | D22: =B22*C22 | E22: =Paramètres!$H$7/365 | F22: =D22*E22
A23: Détection Gaz | B23: =Paramètres!$C$7/Paramètres!$C$3 | C23: ='Récapitulatif 2025'!E101 | D23: =B23*C23 | E23: =Paramètres!$H$7/365 | F23: =D23*E23
A24: Vérifications règlementaires | B24: =Paramètres!$C$7/19945.0 | C24: ='Récapitulatif 2025'!E104 | D24: =B24*C24 | E24: =Paramètres!$H$7/365 | F24: =D24*E24
A25: Portails | B25: =Paramètres!$C$7/Paramètres!$C$3 | C25: ='Récapitulatif 2025'!E107 | D25: =B25*C25 | E25: =Paramètres!$H$7/365 | F25: =D25*E25
A26: Sous-total — CONTRAT MAINTENANCE | C26: =SUM(C14:C25) | D26: =SUM(D14:D25) | F26: =SUM(F14:F25)
A27: ASSURANCES + JURIDIQUE
A28: Assurances | B28: =Paramètres!$C$7/Paramètres!$C$3 | C28: ='Récapitulatif 2025'!E111 | D28: =B28*C28 | E28: =Paramètres!$H$7/365 | F28: =D28*E28
A29: Sous-total — ASSURANCES + JURIDIQUE | C29: =SUM(C28:C28) | D29: =SUM(D28:D28) | F29: =SUM(F28:F28)
A31: HONORAIRES
A32: Honoraires Gestion Technique | E32: 1 | F32: =IF(D32="","",D32*E32)
A33: Sous-total — HONORAIRES | C33: =SUM(C32:C32) | D33: =SUM(D32:D32) | F33: =SUM(F32:F32)
A35: TOTAL CHARGES RÉCUPÉRABLES RÉELLES (€ HT) | C35: =C9+C12+C26+C29+C33 | D35: =D9+D12+D26+D29+D33 | F35: =F9+F12+F26+F29+F33
A37: Provisions pour charges versées | D37: Montant annuel (€) | F37: Montant locataire (€)
A38: 1er trimestre (T1) | F38: 2990.6
A39: 2e trimestre (T2) | F39: 25284.11
A40: 3e trimestre (T3) | F40: 28376.42
A41: 4e trimestre (T4) | F41: 28376.42
A42: Total provisions pour charges versées → | D42: =SUM(D38:D41) | F42: =SUM(F38:F41)
A44: =IF(F35-F42>0,"SOLDE DÉBITEUR","SOLDE CRÉDITEUR") | D44: =D35-D42 | F44: =F35-F42
A46: ℹ Clé répartition = surface lot ÷ surface totale site. Période = nombre de jours d'occupation ÷ 365.

Sheet C3 C4 C5
A1: RÉGULARISATION DE CHARGES — C3 C4 C5
A2: Site : ORMES A | Année 2025
A3: =Paramètres!$B$8&IF(Paramètres!$E$8<>""," — "&Paramètres!$E$8,"")
A4: Poste | B4: Clé répartition | C4: Total site HT | D4: QP annuelle | E4: Période | F4: QP locataire
A5: FLUIDES
A6: Eau | B6: =Paramètres!$C$8/Paramètres!$C$3 | C6: ='Récapitulatif 2025'!E10 | D6: =B6*C6 | E6: =Paramètres!$H$8/365 | F6: =D6*E6
A7: Electricité | B7: =Paramètres!$C$8/Paramètres!$C$3 | C7: ='Récapitulatif 2025'!E21 | D7: =B7*C7 | E7: =Paramètres!$H$8/365 | F7: =D7*E7
A8: Gaz | B8: =Paramètres!$C$8/Paramètres!$C$3 | C8: ='Récapitulatif 2025'!E32 | D8: =B8*C8 | E8: =Paramètres!$H$8/365 | F8: =D8*E8
A9: Sous-total — FLUIDES | C9: =SUM(C6:C8) | D9: =SUM(D6:D8) | F9: =SUM(F6:F8)
A10: TRAVAUX
A11: Entretien Courant | B11: =Paramètres!$C$8/Paramètres!$C$3 | C11: ='Récapitulatif 2025'!E37 | D11: =B11*C11 | E11: =Paramètres!$H$8/365 | F11: =D11*E11
A12: Sous-total — TRAVAUX | C12: =SUM(C11:C11) | D12: =SUM(D11:D11) | F12: =SUM(F11:F11)
A13: CONTRAT MAINTENANCE
A14: Espaces Verts | B14: =Paramètres!$C$8/Paramètres!$C$3 | C14: ='Récapitulatif 2025'!E46 | D14: =B14*C14 | E14: =Paramètres!$H$8/365 | F14: =D14*E14
A15: CVC | B15: =Paramètres!$C$8/Paramètres!$C$3 | C15: ='Récapitulatif 2025'!E50 | D15: =B15*C15 | E15: =Paramètres!$H$8/365 | F15: =D15*E15
A16: Sécurité | B16: =Paramètres!$C$8/Paramètres!$C$3 | C16: ='Récapitulatif 2025'!E54 | D16: =B16*C16 | E16: =Paramètres!$H$8/365 | F16: =D16*E16
A17: SSI | B17: =Paramètres!$C$8/Paramètres!$C$3 | C17: ='Récapitulatif 2025'!E59 | D17: =B17*C17 | E17: =Paramètres!$H$8/365 | F17: =D17*E17
A18: Toitures | B18: =Paramètres!$C$8/Paramètres!$C$3 | C18: ='Récapitulatif 2025'!E64 | D18: =B18*C18 | E18: =Paramètres!$H$8/365 | F18: =D18*E18
A19: SPK / RIA / PI | B19: =Paramètres!$C$8/Paramètres!$C$3 | C19: ='Récapitulatif 2025'!E77 | D19: =B19*C19 | E19: =Paramètres!$H$8/365 | F19: =D19*E19
A20: Installations électriques | B20: =Paramètres!$C$8/35730.0 | C20: ='Récapitulatif 2025'!E83 | D20: =B20*C20 | E20: =Paramètres!$H$8/365 | F20: =D20*E20
A21: Protection Foudre | B21: =Paramètres!$C$8/23820.0 | C21: ='Récapitulatif 2025'!E88 | D21: =B21*C21 | E21: =Paramètres!$H$8/365 | F21: =D21*E21
A22: GTB | B22: =Paramètres!$C$8/Paramètres!$C$3 | C22: ='Récapitulatif 2025'!E97 | D22: =B22*C22 | E22: =Paramètres!$H$8/365 | F22: =D22*E22
A23: Détection Gaz | B23: =Paramètres!$C$8/Paramètres!$C$3 | C23: ='Récapitulatif 2025'!E101 | D23: =B23*C23 | E23: =Paramètres!$H$8/365 | F23: =D23*E23
A24: Vérifications règlementaires | B24: =Paramètres!$C$8/19945.0 | C24: ='Récapitulatif 2025'!E104 | D24: =B24*C24 | E24: =Paramètres!$H$8/365 | F24: =D24*E24
A25: Portails | B25: =Paramètres!$C$8/Paramètres!$C$3 | C25: ='Récapitulatif 2025'!E107 | D25: =B25*C25 | E25: =Paramètres!$H$8/365 | F25: =D25*E25
A26: Sous-total — CONTRAT MAINTENANCE | C26: =SUM(C14:C25) | D26: =SUM(D14:D25) | F26: =SUM(F14:F25)
A27: ASSURANCES + JURIDIQUE
A28: Assurances | B28: =Paramètres!$C$8/Paramètres!$C$3 | C28: ='Récapitulatif 2025'!E111 | D28: =B28*C28 | E28: =Paramètres!$H$8/365 | F28: =D28*E28
A29: Sous-total — ASSURANCES + JURIDIQUE | C29: =SUM(C28:C28) | D29: =SUM(D28:D28) | F29: =SUM(F28:F28)
A31: HONORAIRES
A32: Honoraires Gestion Technique | E32: 1 | F32: =IF(D32="","",D32*E32)
A33: Sous-total — HONORAIRES | C33: =SUM(C32:C32) | D33: =SUM(D32:D32) | F33: =SUM(F32:F32)
A35: TOTAL CHARGES RÉCUPÉRABLES RÉELLES (€ HT) | C35: =C9+C12+C26+C29+C33 | D35: =D9+D12+D26+D29+D33 | F35: =F9+F12+F26+F29+F33
A37: Provisions pour charges versées | D37: Montant annuel (€) | F37: Montant locataire (€)
A38: 1er trimestre (T1)
A39: 2e trimestre (T2)
A40: 3e trimestre (T3)
A41: 4e trimestre (T4)
A42: Total provisions pour charges versées → | D42: =SUM(D38:D41) | F42: =SUM(F38:F41)
A44: =IF(F35-F42>0,"SOLDE DÉBITEUR","SOLDE CRÉDITEUR") | D44: =D35-D42 | F44: =F35-F42
A46: ℹ Clé répartition = surface lot ÷ surface totale site. Période = nombre de jours d'occupation ÷ 365.

Sheet Vacance Locative
A1: ORMES A — COÛT DE LA VACANCE LOCATIVE 2025
A2: Estimation de la perte de charges non récupérées sur les lots vacants
A4: Lot | B4: Statut | C4: Surface (m²) | D4: QP annuelle (€ HT) | E4: Période (j/365) | F4: Coût vacance (€ HT)
A5: =Paramètres!A7 | B5: =Paramètres!B7 | C5: =Paramètres!C7 | D5: ='C1 C2'!D35 | E5: =Paramètres!H7/365 | F5: =IF(Paramètres!B7="Vacant",'C1 C2'!D35,'C1 C2'!D35-'C1 C2'!F35)
A6: =Paramètres!A8 | B6: =Paramètres!B8 | C6: =Paramètres!C8 | D6: ='C3 C4 C5'!D35 | E6: =Paramètres!H8/365 | F6: =IF(Paramètres!B8="Vacant",'C3 C4 C5'!D35,'C3 C4 C5'!D35-'C3 C4 C5'!F35)
A8: Total QP charges (tous lots) | D8: =SUM(D5:D6)
A9: Nombre de lots vacants | D9: =COUNTIF(B5:B6,"Vacant")
A11: Charges non récupérables (Frais Bancaires + CAPEX) | F11: ='Récapitulatif 2025'!E118
A13: TOTAL COÛT DE LA VACANCE LOCATIVE (€ HT) | F13: =F5+F6+F11
A15: Part vacance sur total charges site | F15: =IF(D8>0,F13/D8,0)
A17: ℹ QP annuelle = Total site HT × clé de répartition. Coût vacance = QP annuelle × fraction de l'année non occupée.
